weather_query_xiaomei/__init__.py
weather_query_xiaomei/server.py
weather_query_xiaomei-0.1.0.dist-info/METADATA
weather_query_xiaomei-0.1.0.dist-info/WHEEL
weather_query_xiaomei-0.1.0.dist-info/entry_points.txt
weather_query_xiaomei-0.1.0.dist-info/RECORD
