Metadata-Version: 2.4
Name: weather-query-xiaomei
Version: 0.1.0
Summary: query weather of different city for mt users
Author-email: yangming43 <yangming43@meituan.com>
Requires-Python: >=3.10
Requires-Dist: mcp>=1.1.2
